hfs/__init__.py
hfs/__main__.py
hfs/account.py
hfs/audit.py
hfs/cli.py
hfs/config.py
hfs/diag.py
hfs/health.py
hfs/hf.py
hfs/metrics.py
hfs/policy.py
hfs/redis_client.py
hfs/scheduler.py
hfs/space.py
hfs/state.py
hfs/worker.py
hfs/admin/__init__.py
hfs/admin/__main__.py
hfs/admin/account.py
hfs/admin/bootstrap.py
hfs/admin/health.py
hfs/admin/node.py
hfs/admin/project.py
hfs/admin/space.py
hfs/admin/stats.py
mp_hfs-3.0.5.dist-info/METADATA
mp_hfs-3.0.5.dist-info/WHEEL
mp_hfs-3.0.5.dist-info/entry_points.txt
mp_hfs-3.0.5.dist-info/top_level.txt
mp_hfs-3.0.5.dist-info/RECORD
