Metadata-Version: 2.4
Name: mp-hfs
Version: 3.0.5
Summary: HuggingFace Space Worker 分布式调度系统
Home-page: https://github.com/rally82-2/ai-dev
Author: Rally82
Author-email: rally82@example.com
Classifier: Development Status :: 4 - Beta
Classifier: Intended Audience :: Developers
Classifier: License :: OSI Approved :: MIT License
Classifier: Programming Language :: Python :: 3
Classifier: Programming Language :: Python :: 3.8
Classifier: Programming Language :: Python :: 3.9
Classifier: Programming Language :: Python :: 3.10
Classifier: Programming Language :: Python :: 3.11
Classifier: Programming Language :: Python :: 3.12
Requires-Python: >=3.8
Requires-Dist: redis>=4.0.0
Requires-Dist: requests>=2.25.0
Requires-Dist: click>=8.0.0
Requires-Dist: pyyaml>=5.4.0
Requires-Dist: tabulate>=0.8.9
Dynamic: author
Dynamic: author-email
Dynamic: classifier
Dynamic: description
Dynamic: description-content-type
Dynamic: home-page
Dynamic: requires-dist
Dynamic: requires-python
Dynamic: summary
